{
  "title": "詩文 - 白日夢",
  "slug": "memory-daydream-poem-college",
  "tags": [
    "Writings - 創作"
  ],
  "published_at": "2018-03-28T02:44:00.000Z",
  "type": "post",
  "ghost_id": "67e3a65ce551140001120f09",
  "status": "published",
  "visibility": "public",
  "featured": false,
  "created_at": "2025-03-26T07:01:48.000Z",
  "updated_at": "2025-03-26T13:16:37.000Z",
  "custom_excerpt": "從封存的大學時代舊筆記裡面翻出來的東西，當初不知道是懷著怎麼樣的豪情壯志寫出這一首詩的，這篇好像有投稿到系刊。快畢業了，看看這首詩，真希望還保有那時候的年輕活力呢。",
  "authors": [
    "Gbanyan"
  ],
  "feature_image": "../assets/grassland-daydream-cover.jpg",
  "body": {
    "raw": "\n*從封存的大學時代舊筆記裡面翻出來的東西，當初不知道是懷著怎麼樣的豪情壯志寫出這一首詩的，這篇好像有投稿到系刊。快畢業了，看看這首詩，真希望還保有那時候的年輕活力呢。*\n\n---\n\n啊，在過往記憶與年歲交織的經緯  \n在花開花落，葉翠綠如昔的風鈴木下  \n是回憶，還是夢境?  \n我悄悄的進入了沉眠中  \n  \n 像那天真爛漫的小孩在一望無際的草原上奔跑著，  \n手裡拉著風箏的線，頭仰望著天空  \n天空、大地、吹拂的風，  \n是這世界給我們的滋養，  \n而飛揚的心，不停往更高的地方飛去  \n  \n 不可理喻地，  \n有時也會不由自主哼出一首歌  \n像那吹著魔笛的少年  \n自神祕的魅惑笛音中慵懶懶地進入美夢，  \n  \n幽湖旁、營帳邊  \n仲夏的精靈悄悄遞出了邀請  \n熾熱的渴望，舔食的火舌  \n我在夜晚吉普賽人的火堆旁與愛恨嗔痴起舞，  \n  \n當我身在暗寂的荒谷  \n鬍渣沾著清晨的露水  \n吹起號角，響徹雲霄，  \n冷冽的鋼鐵，映照著揚起的嘴角  \n要像風塵俠客，行走過這血腥江湖?  \n粗獷遊俠，踏過杳無人跡的草原?  \n馬兒嘶鳴，出鞘寶劍鑲著堅決，  \n心目中自己的身影與英雄重疊  \n瘦弱的少年何時能成長，披上責任的重甲?  \n流落的王族何時能復返，戴上榮耀的王冠?  \n振臂一揮，怒眼鷹眉燃著果決，  \n我向那黎明晨曦策馬直奔。\n\n---\n",
    "html": "<p><em>從封存的大學時代舊筆記裡面翻出來的東西，當初不知道是懷著怎麼樣的豪情壯志寫出這一首詩的，這篇好像有投稿到系刊。快畢業了，看看這首詩，真希望還保有那時候的年輕活力呢。</em></p>\n<hr>\n<p>啊，在過往記憶與年歲交織的經緯<br>\n在花開花落，葉翠綠如昔的風鈴木下<br>\n是回憶，還是夢境?<br>\n我悄悄的進入了沉眠中</p>\n<p> 像那天真爛漫的小孩在一望無際的草原上奔跑著，<br>\n手裡拉著風箏的線，頭仰望著天空<br>\n天空、大地、吹拂的風，<br>\n是這世界給我們的滋養，<br>\n而飛揚的心，不停往更高的地方飛去</p>\n<p> 不可理喻地，<br>\n有時也會不由自主哼出一首歌<br>\n像那吹著魔笛的少年<br>\n自神祕的魅惑笛音中慵懶懶地進入美夢，</p>\n<p>幽湖旁、營帳邊<br>\n仲夏的精靈悄悄遞出了邀請<br>\n熾熱的渴望，舔食的火舌<br>\n我在夜晚吉普賽人的火堆旁與愛恨嗔痴起舞，</p>\n<p>當我身在暗寂的荒谷<br>\n鬍渣沾著清晨的露水<br>\n吹起號角，響徹雲霄，<br>\n冷冽的鋼鐵，映照著揚起的嘴角<br>\n要像風塵俠客，行走過這血腥江湖?<br>\n粗獷遊俠，踏過杳無人跡的草原?<br>\n馬兒嘶鳴，出鞘寶劍鑲著堅決，<br>\n心目中自己的身影與英雄重疊<br>\n瘦弱的少年何時能成長，披上責任的重甲?<br>\n流落的王族何時能復返，戴上榮耀的王冠?<br>\n振臂一揮，怒眼鷹眉燃著果決，<br>\n我向那黎明晨曦策馬直奔。</p>\n<hr>"
  },
  "_id": "posts/詩文 - 白日夢.md",
  "_raw": {
    "sourceFilePath": "posts/詩文 - 白日夢.md",
    "sourceFileName": "詩文 - 白日夢.md",
    "sourceFileDir": "posts",
    "contentType": "markdown",
    "flattenedPath": "posts/詩文 - 白日夢"
  },
  "__ignoredType": "Post",
  "url": "/blog/memory-daydream-poem-college",
  "flattenedPath": "詩文 - 白日夢"
}